Metadata-Version: 2.1
Name: django-binary-database-files
Version: 1.0.17
Summary: A storage system for Django that stores uploaded files in both the database and file system.
Home-page: https://github.com/kimetrica/django-binary-database-files/
Author: Roger Hunwicks
Author-email: roger@tonic-solutions.com
License: UNKNOWN
Platform: UNKNOWN
Classifier: Development Status :: 6 - Mature
Classifier: Framework :: Django
Classifier: Intended Audience :: Developers
Classifier: License :: OSI Approved :: BSD License
Classifier: Operating System :: OS Independent
Classifier: Programming Language :: Python
Classifier: Programming Language :: Python :: 3.6
Classifier: Programming Language :: Python :: 3.7
Classifier: Programming Language :: Python :: 3.8
Classifier: Programming Language :: Python :: 3.9
Classifier: Programming Language :: Python :: 3.10
Classifier: Framework :: Django :: 2.2
Classifier: Framework :: Django :: 3.0
Classifier: Framework :: Django :: 3.1
Classifier: Framework :: Django :: 3.2
Classifier: Framework :: Django :: 4.0
Requires-Python: >=3.6,<3.11
License-File: LICENSE
